s3selectparser.py
s3selectparser-0.0.1.dist-info/LICENSE
s3selectparser-0.0.1.dist-info/METADATA
s3selectparser-0.0.1.dist-info/WHEEL
s3selectparser-0.0.1.dist-info/top_level.txt
s3selectparser-0.0.1.dist-info/RECORD
