Metadata-Version: 2.1
Name: s3selectparser
Version: 0.0.1
Summary: Experimental S3 Select Parser
Home-page: https://github.com/michalc/s3selectparser
Author: Michal Charemza
Author-email: michal@charemza.name
License: UNKNOWN
Platform: UNKNOWN
Classifier: Programming Language :: Python :: 3
Classifier: Programming Language :: SQL
Classifier: License :: OSI Approved :: MIT License
Classifier: Operating System :: OS Independent
Requires-Python: >=3.7.1
Requires-Dist: pyparsing (>=2.4.7)
